core/__init__.py
core/constants.py
core/utils.py
core/io/__init__.py
core/io/bed.py
core/io/fai.py
core/io/repeat_tracks.py
core/io/vcf.py
core/variant/__init__.py
core/variant/filters.py
core/variant/genome_context.py
core/variant/intervals.py
core/variant/sv.py
core/vis/__init__.py
core/vis/plotting_utils.py
core/vis/upset.py
engine/__init__.py
engine/config_utils.py
engine/consensus.py
engine/eval.py
engine/report.py
tests/__init__.py
tests/test_vcf_reader.py
varianteval-0.0.10.dist-info/LICENSE
varianteval-0.0.10.dist-info/METADATA
varianteval-0.0.10.dist-info/WHEEL
varianteval-0.0.10.dist-info/entry_points.txt
varianteval-0.0.10.dist-info/top_level.txt
varianteval-0.0.10.dist-info/RECORD
