Metadata-Version: 2.1
Name: varianteval
Version: 0.0.10
Summary: Library to help compare VCF files
Home-page: https://broadinstitute.github.io/varianteval/
Author: Kiran V Garimella
Author-email: kiran@broadinstitute.org
License: BSD 3-Clause
Platform: UNKNOWN
Classifier: Development Status :: 3 - Alpha
Classifier: Intended Audience :: Science/Research
Classifier: License :: OSI Approved :: BSD License
Classifier: Natural Language :: English
Classifier: Operating System :: OS Independent
Classifier: Programming Language :: Python :: 3.6
Classifier: Programming Language :: Python :: 3.7
Classifier: Programming Language :: Python :: 3.8
Classifier: Programming Language :: Python :: Implementation :: CPython
Requires-Python: >=3.6
Requires-Dist: click
Requires-Dist: click-log
Requires-Dist: cython
Requires-Dist: matplotlib
Requires-Dist: mypy
Requires-Dist: numpy
Requires-Dist: pandas
Requires-Dist: pysam
Requires-Dist: tqdm
